git_auto_export/__init__.py
git_auto_export/apps.py
git_auto_export/signals.py
git_auto_export/tasks.py
git_auto_export/test_settings.py
git_auto_export/urls.py
git_auto_export/wsgi.py
edx_git_auto_export-0.3.dist-info/LICENSE
edx_git_auto_export-0.3.dist-info/METADATA
edx_git_auto_export-0.3.dist-info/WHEEL
edx_git_auto_export-0.3.dist-info/top_level.txt
edx_git_auto_export-0.3.dist-info/RECORD
